gender_spacy/__init__.py
gender_spacy/components.py
gender_spacy/gender_spacy.py
gender_spacy/data/gender_pronouns.csv
gender_spacy/data/project.toml
gender_spacy/data/pronoun_patterns
gender_spacy-0.0.5.dist-info/METADATA
gender_spacy-0.0.5.dist-info/WHEEL
gender_spacy-0.0.5.dist-info/top_level.txt
gender_spacy-0.0.5.dist-info/RECORD
