Metadata-Version: 2.1
Name: gender-spacy
Version: 0.0.5
Summary: A spaCy component for identifying grammatical gender in English texts.
Author: WJB Mattingly
Requires-Dist: pandas <2.0.0,>=1.0.0
Requires-Dist: spacy >=3.4.0
Requires-Dist: spacy-transformers >=1.1.8
Requires-Dist: toml >=0.10.0
